odoo8_addon_l10n_pt_municipality-8.0.1.0.0.99.dev2-py2.7-nspkg.pth
odoo8_addon_l10n_pt_municipality-8.0.1.0.0.99.dev2.dist-info/top_level.txt
odoo8_addon_l10n_pt_municipality-8.0.1.0.0.99.dev2.dist-info/WHEEL
odoo8_addon_l10n_pt_municipality-8.0.1.0.0.99.dev2.dist-info/RECORD
odoo8_addon_l10n_pt_municipality-8.0.1.0.0.99.dev2.dist-info/metadata.json
odoo8_addon_l10n_pt_municipality-8.0.1.0.0.99.dev2.dist-info/DESCRIPTION.rst
odoo8_addon_l10n_pt_municipality-8.0.1.0.0.99.dev2.dist-info/METADATA
odoo8_addon_l10n_pt_municipality-8.0.1.0.0.99.dev2.dist-info/namespace_packages.txt
odoo_addons/l10n_pt_municipality/__openerp__.py
odoo_addons/l10n_pt_municipality/__init__.py
odoo_addons/l10n_pt_municipality/README.rst
odoo_addons/l10n_pt_municipality/data/res.partner.lau.csv
odoo_addons/l10n_pt_municipality/static/description/icon.png
