Metadata-Version: 2.0
Name: odoo8-addon-l10n-pt-municipality
Version: 8.0.1.0.0.99.dev2
Summary: Support for PT municipalities through Eurostat LAUs
Home-page: https://odoo-community.org/
Author: UNKNOWN
Author-email: UNKNOWN
License: AGPL-3
Platform: UNKNOWN
Requires-Dist: odoo (<9.0a,>=8.0a)
Requires-Dist: odoo8-addon-base-location-lau
Classifier: Programming Language :: Python :: 2.7
Classifier: Framework :: Odoo
Classifier: License :: OSI Approved :: GNU Affero General Public License v3
